{
  "scheme_name": "Compensation for Livestock Loss Caused by Wild Animals",
  "scheme_url": "https://www.myscheme.gov.in/schemes/cfllcbwa",
  "location_name": "Madhya Pradesh",
  "location_type": "state",
  "page_title": "Compensation for Livestock Loss Caused by Wild Animals",
  "scraped_at": "2026-03-12 05:53:35 UTC",
  "sections": {
    "details": [
      "The “Compensation for Livestock Loss Caused by Wild Animals” scheme is launched by the Forest Department, Government of Madhya Pradesh. The scheme aims to provide financial relief to individuals whose livestock is injured or killed by wild animals. The scheme applies to both urban and rural areas and covers a variety of livestock including cows, buffaloes, camels, goats, sheep, donkeys, mules, and pigs."
    ],
    "benefits": [
      "Compensation Amounts:",
      "Dairy animals (cow, buffalo, camel): ₹30,000",
      "Sheep/Goat: ₹3,000",
      "Non-dairy animals (bull, buffalo, camel, horse): ₹25,000",
      "Young animals (calf of cow/buffalo/horse/camel), Donkey/Mule: ₹16,000",
      "Pig: ₹3,000",
      "Injury Compensation:",
      "50% of the amount payable for injury under revenue circular provisions.",
      "Mode of Disbursement:",
      "Compensation is paid directly to the beneficiary via e-payment.",
      "Expected Time of Disbursement:",
      "Compensation is provided within 30 working days of claim verification."
    ],
    "eligibility": [
      "The applicant must be a resident of Madhya Pradesh.",
      "The applicant should be the owner of the livestock injured or killed by wild animals."
    ],
    "application_process": {
      "offline": [
        "Registration",
        "Step 1:",
        "Visit the Official Website of \"",
        "Madhya Pradesh Lok Sewa Guarantee Portal",
        "\".",
        "Step 2:",
        "On the homepage, click \"Citizen Registration\". You will be taken to the registration page.",
        "Step 3:",
        "On the registration page, fill in all the mandatory fields (name, mobile number, gender, and captcha) and click \"Verify Mobile Number.\"",
        "Step 4:",
        "A verification code will be sent to your mobile number. Enter the code and complete the registration.",
        "Application",
        "Visit the Official Website of \"Madhya Pradesh Lok Sewa Guarantee Portal\".",
        "Enter your User ID, Password, and Captcha Code, and click \"Login.\"",
        "Click on \"Apply Online Service\" and select the scheme you intend to apply for.",
        "In the scheme's online application form, fill in all the mandatory fields and upload all the mandatory documents in the specified format and size (fields marked with * are mandatory), and click \"Submit\".",
        "Note 1:",
        "The incident must be reported within 48 hours to the nearest Forest Range Officer, either verbally or in writing.",
        "Note 2:",
        "The dead or injured animal should remain at the site for verification by the forest authority."
      ]
    },
    "documents_required": [
      "Identity Proof",
      "Resident Proof",
      "Bank Account Details",
      "Death Certificate",
      "Treatment Bills",
      "Other Necessary Documents, if required"
    ],
    "sources_and_references": [
      "Guidelines"
    ]
  },
  "faqs": [
    {
      "question": "Who is eligible to apply?",
      "answer": "Any livestock owner in Madhya Pradesh whose animals are killed or injured by wild animals."
    },
    {
      "question": "Which animals are covered?",
      "answer": "Cow, buffalo, camel, bull, horse, sheep, goat, donkey, mule, and pig."
    },
    {
      "question": "What is the compensation for injury to livestock?",
      "answer": "50% of the applicable compensation amount under revenue circular provisions."
    },
    {
      "question": "What is the application fee?",
      "answer": "The application is free of cost."
    },
    {
      "question": "Where should the application be submitted?",
      "answer": "At the nearest Forest Range Office or online at mpedistrict.gov.in"
    },
    {
      "question": "Within what time should the incident be reported?",
      "answer": "The incident be reported within 48 hours of occurrence."
    },
    {
      "question": "What is the expected time for payment?",
      "answer": "Payment within 30 working days of verification."
    },
    {
      "question": "How is the compensation disbursed?",
      "answer": "Directly to the beneficiary via e-payment."
    },
    {
      "question": "What if my application is rejected?",
      "answer": "A first appeal can be filed within 30 days, and a second appeal within 60 days."
    },
    {
      "question": "Are urban livestock owners eligible?",
      "answer": "Yes, both urban and rural livestock owners are eligible."
    },
    {
      "question": "Can I move the dead animal before verification?",
      "answer": "No, the dead animal must remain at the site for verification by the Forest Officer."
    }
  ]
}